colab2pdf/__about__.py
colab2pdf/__init__.py
colab2pdf-1.0.0.dist-info/METADATA
colab2pdf-1.0.0.dist-info/WHEEL
colab2pdf-1.0.0.dist-info/licenses/LICENSE
colab2pdf-1.0.0.dist-info/RECORD
