Metadata-Version: 2.1
Name: colab2pdf
Version: 1.0.0
Project-URL: Documentation, https://github.com/unknown/colab2pdf#readme
Project-URL: Issues, https://github.com/unknown/colab2pdf/issues
Project-URL: Source, https://github.com/unknown/colab2pdf
Author-email: Jonathan Agustin <jonathanagustin@gmail.com>
License-Expression: MIT
License-File: LICENSE
Classifier: Development Status :: 4 - Beta
Classifier: Programming Language :: Python
Classifier: Programming Language :: Python :: 3.7
Classifier: Programming Language :: Python :: 3.8
Classifier: Programming Language :: Python :: 3.9
Classifier: Programming Language :: Python :: 3.10
Classifier: Programming Language :: Python :: 3.11
Classifier: Programming Language :: Python :: Implementation :: CPython
Classifier: Programming Language :: Python :: Implementation :: PyPy
Requires-Python: >=3.7
